vfxnaming/__init__.py
vfxnaming/error.py
vfxnaming/logger.py
vfxnaming/naming.py
vfxnaming/rules.py
vfxnaming/serialize.py
vfxnaming/tokens.py
vfxnaming/cfg/config.json
vfxnaming-1.5.9b0.dist-info/LICENSE
vfxnaming-1.5.9b0.dist-info/METADATA
vfxnaming-1.5.9b0.dist-info/WHEEL
vfxnaming-1.5.9b0.dist-info/top_level.txt
vfxnaming-1.5.9b0.dist-info/RECORD
