Metadata-Version: 2.2
Name: vfxnaming
Version: 1.5.9b0
Summary: VFX Naming Conventions Framework
Author-email: Chris Granados <info@chrisgranados.com>
Project-URL: Repository, https://github.com/xiancg/vfxnaming
Project-URL: Documentation, https://naming-conventions.readthedocs.io/en/latest/
Keywords: vfx,games,naming,convention,gaming,tech,art,pipeline
Classifier: Development Status :: 4 - Beta
Classifier: Intended Audience :: Developers
Classifier: Programming Language :: Python :: 3.7
Classifier: License :: OSI Approved :: MIT License
Classifier: Operating System :: OS Independent
Requires-Python: >=3.7
License-File: LICENSE
Provides-Extra: tests
Requires-Dist: pytest; extra == "tests"
Requires-Dist: pytest-cov; extra == "tests"
Requires-Dist: pytest-datafiles; extra == "tests"
Requires-Dist: python-coveralls; extra == "tests"
Requires-Dist: flake8; extra == "tests"
Provides-Extra: lint
Requires-Dist: ruff; extra == "lint"
Provides-Extra: docs
Requires-Dist: sphinx; extra == "docs"
Requires-Dist: sphinx_rtd_theme; extra == "docs"
Provides-Extra: build
Requires-Dist: setuptools; extra == "build"
Requires-Dist: twine; extra == "build"
Requires-Dist: wheel; extra == "build"
Requires-Dist: build; extra == "build"
